dummypdf/__init__.py
dummypdf/__main__.py
dummypdf/errors.py
dummypdf/pdf.py
dummypdf-2.1.0.dist-info/AUTHORS
dummypdf-2.1.0.dist-info/LICENSE
dummypdf-2.1.0.dist-info/METADATA
dummypdf-2.1.0.dist-info/WHEEL
dummypdf-2.1.0.dist-info/entry_points.txt
dummypdf-2.1.0.dist-info/top_level.txt
dummypdf-2.1.0.dist-info/zip-safe
dummypdf-2.1.0.dist-info/RECORD
