Metadata-Version: 2.1
Name: dummypdf
Version: 2.1.0
Summary: Generate dummy pdf files with configurable paper size and number of pages.
Home-page: http://framagit.org/spalax/dummypdf
Author: Louis Paternault
Author-email: spalax@gresille.org
License: GPLv3 or any later version
Project-URL: Documentation, http://dummypdf.readthedocs.io
Project-URL: Source, https://framagit.org/spalax/dummypdf
Project-URL: Tracker, https://framagit.org/spalax/dummypdf/issues
Keywords: pdf dummy test
Classifier: Development Status :: 5 - Production/Stable
Classifier: Environment :: Console
Classifier: Intended Audience :: Developers
Classifier: License :: OSI Approved :: GNU General Public License v3 or later (GPLv3+)
Classifier: Operating System :: OS Independent
Classifier: Programming Language :: Python
Classifier: Programming Language :: Python :: 3
Classifier: Programming Language :: Python :: 3.8
Classifier: Programming Language :: Python :: 3.9
Classifier: Programming Language :: Python :: 3.10
Classifier: Programming Language :: Python :: 3.11
Classifier: Programming Language :: Python :: 3.12
Classifier: Programming Language :: Python :: 3.13
Classifier: Topic :: Utilities
Requires-Python: <4,>=3.8
License-File: LICENSE
License-File: AUTHORS
Requires-Dist: papersize
Requires-Dist: reportlab
